pac_synth-0.0.8.dist-info/METADATA
pac_synth-0.0.8.dist-info/WHEEL
pac_synth-0.0.8.dist-info/license_files/LICENSE
pacsynth/__init__.py
pacsynth/pacsynth.abi3.so
pac_synth-0.0.8.dist-info/RECORD
