Metadata-Version: 2.1
Name: pac-synth
Version: 0.0.8
Classifier: Programming Language :: Rust
Classifier: Programming Language :: Python :: Implementation :: CPython
Classifier: Programming Language :: Python :: Implementation :: PyPy
License-File: LICENSE
Summary: Private Accurate Combination (PAC) Synthesizers
Author-email: Synthetic Data Showcase Team <sds-team@microsoft.com>, Darren Edge <darren.edge@microsoft.com>, Derek Worthen <derek.worthen@microsoft.com>, Nathan Evans <nathan.evans@microsoft.com>, Rodrigo Racanicci <rracanicci@microsoft.com>
Maintainer-email: Rodrigo Racanicci <rracanicci@microsoft.com>
License: MIT
Requires-Python: >=3.7
Project-URL: Source Code, https://github.com/microsoft/synthetic-data-showcase
